commit_pyl1nt-1.0.7.data/scripts/pyl1nter
commit_pyl1nt-1.0.7.dist-info/METADATA
commit_pyl1nt-1.0.7.dist-info/RECORD
commit_pyl1nt-1.0.7.dist-info/WHEEL
commit_pyl1nt-1.0.7.dist-info/top_level.txt
pyl1nter/__init__.py
pyl1nter/app.py
pyl1nter/utils.py
